labvirtual/simulador_aeropendulo/README.md
labvirtual/simulador_aeropendulo/__init__.py
labvirtual/simulador_aeropendulo/animacao_aeropendulo.py
labvirtual/simulador_aeropendulo/docs/Modelagem_matematica_do_aeropendulo.ipynb
labvirtual/simulador_aeropendulo/docs/aeropendulo_doc.html
labvirtual/simulador_aeropendulo/docs/diagramas/diagrama_estrutura_codigo copy.drawio
labvirtual/simulador_aeropendulo/docs/diagramas/diagrama_estrutura_codigo copy.png
labvirtual/simulador_aeropendulo/docs/diagramas/diagrama_estrutura_codigo.drawio
labvirtual/simulador_aeropendulo/docs/diagramas/diagrama_estrutura_codigo.png
labvirtual/simulador_aeropendulo/docs/diagramas/diagrama_estrutura_codigo.svg
labvirtual/simulador_aeropendulo/docs/diagramas/diagrama_estrutura_codigo1.png
labvirtual/simulador_aeropendulo/docs/projeto_de_controladores/projeto_controlador_por_lgr/ControlSystemDesignerSession1.mat
labvirtual/simulador_aeropendulo/docs/projeto_de_controladores/projeto_controlador_por_lgr/ControlSystemDesignerSession2.mat
labvirtual/simulador_aeropendulo/docs/projeto_de_controladores/projeto_controlador_por_lgr/projeto_controlador_lgr.m
labvirtual/simulador_aeropendulo/docs/utils/Template_Artigos_ST_COBENGE-2023.docx.pdf
labvirtual/simulador_aeropendulo/docs/utils/Template_Dissertacao_NDAE.docx
labvirtual/simulador_aeropendulo/docs/utils/Template_TCC_CAMTUC.docx
labvirtual/simulador_aeropendulo/docs/utils/aeropendulo_1.png
labvirtual/simulador_aeropendulo/docs/utils/demo_gif.gif
labvirtual/simulador_aeropendulo/docs/utils/diagrama_bloco_aeropendulo_nao_linear.drawio
labvirtual/simulador_aeropendulo/docs/utils/diagrama_bloco_aeropendulo_nao_linear.svg
labvirtual/simulador_aeropendulo/docs/utils/favicon_aeropendulo_png.png
labvirtual/simulador_aeropendulo/docs/utils/lab_virtual.png
labvirtual/simulador_aeropendulo/docs/utils/logo_ufpa.png
labvirtual/simulador_aeropendulo/docs/utils/logoufpa.png
labvirtual/simulador_aeropendulo/docs/utils/media_discordapp_net-image (1).txt
labvirtual-0.3.21.dist-info/LICENSE
labvirtual-0.3.21.dist-info/METADATA
labvirtual-0.3.21.dist-info/WHEEL
labvirtual-0.3.21.dist-info/RECORD
