Metadata-Version: 2.1
Name: labvirtual
Version: 0.3.21
Summary: Biblioteca de simulação gráfica 3D de ambientes para estudo de controle de sistema.
Author: Oseiasdfarias
Author-email: oseias.dfarias@gmail.com
Requires-Python: >=3.8,<=3.11
Classifier: Programming Language :: Python :: 3
Classifier: Programming Language :: Python :: 3.8
Classifier: Programming Language :: Python :: 3.9
Classifier: Programming Language :: Python :: 3.10
Classifier: Programming Language :: Python :: 3.11
Requires-Dist: control (>=0.9.3.post2,<0.10.0)
Requires-Dist: numpy (>=1.24.3,<2.0.0)
Requires-Dist: scipy (>=1.10.1,<2.0.0)
Requires-Dist: vpython (>=7.6.4,<8.0.0)
